clippy_mcp/__init__.py
clippy_mcp/app.py
clippy_mcp/config.py
clippy_mcp/console.py
clippy_mcp/context.py
clippy_mcp/context_dependent.py
clippy_mcp/event_progress.py
clippy_mcp/mcp_server_registry.py
clippy_mcp/progress_display.py
clippy_mcp/py.typed
clippy_mcp/agents/__init__.py
clippy_mcp/agents/agent.py
clippy_mcp/cli/__init__.py
clippy_mcp/cli/__main__.py
clippy_mcp/cli/main.py
clippy_mcp/cli/terminal.py
clippy_mcp/cli/commands/config.py
clippy_mcp/core/decorator_app.py
clippy_mcp/data/artificial_analysis_llm_benchmarks.json
clippy_mcp/eval/__init__.py
clippy_mcp/executor/__init__.py
clippy_mcp/executor/decorator_registry.py
clippy_mcp/executor/executor.py
clippy_mcp/executor/task_registry.py
clippy_mcp/executor/temporal.py
clippy_mcp/executor/workflow.py
clippy_mcp/executor/workflow_signal.py
clippy_mcp/human_input/__init__.py
clippy_mcp/human_input/handler.py
clippy_mcp/human_input/types.py
clippy_mcp/logging/__init__.py
clippy_mcp/logging/events.py
clippy_mcp/logging/json_serializer.py
clippy_mcp/logging/listeners.py
clippy_mcp/logging/logger.py
clippy_mcp/logging/rich_progress.py
clippy_mcp/logging/tracing.py
clippy_mcp/logging/transport.py
clippy_mcp/mcp/__init__.py
clippy_mcp/mcp/gen_client.py
clippy_mcp/mcp/mcp_activity.py
clippy_mcp/mcp/mcp_agent_client_session.py
clippy_mcp/mcp/mcp_agent_server.py
clippy_mcp/mcp/mcp_aggregator.py
clippy_mcp/mcp/mcp_connection_manager.py
clippy_mcp/mcp/stdio.py
clippy_mcp/telemetry/__init__.py
clippy_mcp/telemetry/usage_tracking.py
clippy_mcp/workflows/__init__.py
clippy_mcp/workflows/embedding/__init__.py
clippy_mcp/workflows/embedding/embedding_base.py
clippy_mcp/workflows/embedding/embedding_cohere.py
clippy_mcp/workflows/embedding/embedding_openai.py
clippy_mcp/workflows/evaluator_optimizer/__init__.py
clippy_mcp/workflows/evaluator_optimizer/evaluator_optimizer.py
clippy_mcp/workflows/intent_classifier/__init__.py
clippy_mcp/workflows/intent_classifier/intent_classifier_base.py
clippy_mcp-0.0.8.dist-info/METADATA
clippy_mcp-0.0.8.dist-info/WHEEL
clippy_mcp-0.0.8.dist-info/entry_points.txt
clippy_mcp-0.0.8.dist-info/licenses/LICENSE
clippy_mcp-0.0.8.dist-info/RECORD
